molscrub/__init__.py
molscrub/amine_flip.py
molscrub/common.py
molscrub/core.py
molscrub/espaloma_minim.py
molscrub/geometry.py
molscrub/protonate.py
molscrub/ringfix.py
molscrub/storage.py
molscrub/utils.py
molscrub/data/pka_reactions.txt
molscrub/data/tautomers.txt
molscrub-0.2.2.data/data/LICENSE
molscrub-0.2.2.data/data/README.md
molscrub-0.2.2.data/data/scripts/scrub.py
molscrub-0.2.2.data/scripts/scrub.py
molscrub-0.2.2.dist-info/licenses/LICENSE
molscrub-0.2.2.dist-info/METADATA
molscrub-0.2.2.dist-info/WHEEL
molscrub-0.2.2.dist-info/top_level.txt
molscrub-0.2.2.dist-info/RECORD
