Metadata-Version: 2.4
Name: molscrub
Version: 0.2.2
Summary: Enumerate states of small organic molecules: 3D coordinates, tautomers, pH-based adjustments
Home-page: https://github.com/forlilab/molscrub
Author: Forli Lab
Author-email: forli@scripps.edu
License: GPL-v3
Requires-Python: >=3.9
License-File: LICENSE
Requires-Dist: rdkit>=2022.03.1
Dynamic: author
Dynamic: author-email
Dynamic: description
Dynamic: description-content-type
Dynamic: home-page
Dynamic: license
Dynamic: license-file
Dynamic: requires-dist
Dynamic: requires-python
Dynamic: summary
